<PAMDataset>
  <PAMRasterBand band="1">
    <Description>Layer_1</Description>
    <Metadata>
      <MDI key="LAYER_TYPE">athematic</MDI>
      <MDI key="STATISTICS_MINIMUM">0.35886377096176</MDI>
      <MDI key="STATISTICS_MAXIMUM">0.40602600574493</MDI>
      <MDI key="STATISTICS_MEAN">0.39293577782214</MDI>
      <MDI key="STATISTICS_STDDEV">0.013487462143894</MDI>
      <MDI key="STATISTICS_SKIPFACTORX">1</MDI>
      <MDI key="STATISTICS_SKIPFACTORY">1</MDI>
      <MDI key="STATISTICS_EXCLUDEDVALUES"></MDI>
      <MDI key="STATISTICS_COVARIANCES">1.81911635082975E-04</MDI>
    </Metadata>
  </PAMRasterBand>
</PAMDataset>
